calculator_lib/__init__.py
calculator_lib/operations.py
calculator_lib_henriqk0-0.1.0.dist-info/METADATA
calculator_lib_henriqk0-0.1.0.dist-info/WHEEL
calculator_lib_henriqk0-0.1.0.dist-info/top_level.txt
calculator_lib_henriqk0-0.1.0.dist-info/RECORD
